{
  "id": 2000217359,
  "first_name": "Danilo",
  "last_name": "Peu",
  "birth_date": "2003-03-22",
  "country_id": 1651,
  "club_id": 314600,
  "positions": [
    {
      "code": "AML",
      "level": 20
    },
    {
      "code": "ST",
      "level": 20
    }
  ],
  "current_ability": 81,
  "potential_ability": 94,
  "value": 14000,
  "contract": {
    "salary": 0,
    "expiration": "2033-06-30",
    "started": "2025-07-01",
    "contract_type": "FullTime"
  },
  "loan": {
    "to_club_id": 331,
    "expiration": "2026-11-30",
    "salary": 0,
    "wage_contribution_pct": 100
  }
}