{
  "id": 14178665,
  "first_name": "Mateo",
  "last_name": "Klimowicz",
  "birth_date": "2000-07-06",
  "country_id": 771,
  "club_id": 1445,
  "positions": [
    {
      "code": "AML",
      "level": 20
    },
    {
      "code": "AMC",
      "level": 20
    }
  ],
  "current_ability": 91,
  "potential_ability": 111,
  "value": 285000,
  "contract": {    "expiration": "2030-06-30",
    "started": "2025-07-01",
    "contract_type": "FullTime"
  },
  "ids": {
    "transfermarkt.com": "540302"
  },
  "history": [
    { "s": 2020, "c": 960, "p": 25, "g": 1 },
    { "s": 2021, "c": 960, "p": 15 }
  ]
}