{
  "id": 2000453416,
  "first_name": "Santiago",
  "last_name": "Yepes",
  "birth_date": "2007-03-05",
  "country_id": 1653,
  "club_id": 309348,
  "positions": [
    {
      "code": "DC",
      "level": 20
    }
  ],
  "current_ability": 60,
  "potential_ability": 97,
  "value": 161000,
  "contract": {
    "salary": 0,
    "expiration": "2027-12-31",
    "started": "2025-07-01",
    "contract_type": "FullTime"
  },
  "loan": {
    "to_club_id": 2000235756,
    "expiration": "2028-11-30",
    "salary": 0,
    "wage_contribution_pct": 100
  }
}