{
  "id": 24015076,
  "first_name": "Ante",
  "last_name": "Vuković",
  "birth_date": "1990-04-10",
  "country_id": 761,
  "club_id": 129872,
  "positions": [
    {
      "code": "DR",
      "level": 20
    },
    {
      "code": "WBR",
      "level": 16
    },
    {
      "code": "MR",
      "level": 16
    }
  ],
  "current_ability": 54,
  "potential_ability": 66,
  "value": 0,
  "contract": {
    "salary": 0,
    "expiration": "2020-06-30",
    "started": "2025-07-01",
    "contract_type": "Amateur"
  }
}