{
  "id": 619,
  "name": "Bristol City",
  "location": {
    "city_id": 3606
  },
  "finance": {
    "balance": 10160000
  },
  "teams": [
    {
      "id": 619,
      "name": "Bristol City",
      "slug": "bristol-city",
      "team_type": "Main",
      "reputation": {
        "home": 5800,
        "national": 5800,
        "world": 5800
      }
    },
    {
      "id": 90700013,
      "name": "Bristol City",
      "slug": "bristol-city-u20",
      "team_type": "U20",
      "reputation": {
        "home": 1740,
        "national": 1740,
        "world": 1740
      }
    },
    {
      "id": 90700014,
      "name": "Bristol City",
      "slug": "bristol-city-u18",
      "team_type": "U18",
      "reputation": {
        "home": 1160,
        "national": 1160,
        "world": 1160
      }
    }
  ],
  "colors": {
    "background": "#e2001a",
    "foreground": "#ffffff"
  },
  "philosophy": "Balanced",
  "facilities": {
    "training": "Excellent",
    "youth": "Great",
    "academy": "Adequate",
    "recruitment": "Adequate"
  },
  "average_attendance": 22423
}