{
  "id": 2000115209,
  "first_name": "Daniil",
  "last_name": "Checher",
  "birth_date": "2004-11-17",
  "country_id": 800,
  "club_id": 71105155,
  "positions": [
    {
      "code": "DC",
      "level": 20
    },
    {
      "code": "DM",
      "level": 20
    }
  ],
  "current_ability": 62,
  "potential_ability": 99,
  "value": 589000,
  "contract": {
    "salary": 0,
    "expiration": "2027-06-30",
    "started": "2025-07-01",
    "contract_type": "FullTime"
  },
  "ids": {
    "transfermarkt.com": "1173335"
  }
}