{
  "id": 2000109788,
  "first_name": "Jhosefer",
  "last_name": "",
  "birth_date": "2004-03-09",
  "country_id": 1651,
  "club_id": 107205,
  "positions": [
    {
      "code": "WBR",
      "level": 20
    },
    {
      "code": "AMR",
      "level": 20
    },
    {
      "code": "AML",
      "level": 20
    },
    {
      "code": "AMC",
      "level": 20
    }
  ],
  "current_ability": 75,
  "potential_ability": 96,
  "value": 393000,
  "contract": {    "expiration": "2034-06-30",
    "started": "2025-07-01",
    "contract_type": "FullTime"
  }
}