{
  "id": 2000334921,
  "first_name": "Dominik",
  "last_name": "Thaqi",
  "birth_date": "2007-02-02",
  "country_id": 761,
  "club_id": 441,
  "positions": [
    {
      "code": "AMR",
      "level": 20
    },
    {
      "code": "AML",
      "level": 20
    },
    {
      "code": "AMC",
      "level": 20
    }
  ],
  "current_ability": 88,
  "potential_ability": 109,
  "value": 147000,
  "contract": {
    "salary": 0,
    "expiration": "2028-06-30",
    "started": "2025-07-01",
    "contract_type": "FullTime"
  }
}