{
  "id": 2000431244,
  "first_name": "Ammar",
  "last_name": "Al-Hudaybi",
  "birth_date": "2006-12-27",
  "country_id": 133,
  "club_id": 7920359,
  "positions": [
    {
      "code": "DL",
      "level": 20
    },
    {
      "code": "WBL",
      "level": 16
    },
    {
      "code": "AML",
      "level": 16
    }
  ],
  "current_ability": 67,
  "potential_ability": 102,
  "value": 93000,
  "contract": {    "expiration": "2036-06-30",
    "started": "2025-07-01",
    "contract_type": "FullTime"
  },
  "ids": {
    "transfermarkt.com": "1349851"
  }
}
