{
  "id": 95076452,
  "first_name": "Liad",
  "last_name": "Levi",
  "birth_date": "2003-09-23",
  "country_id": 775,
  "club_id": 7861698,
  "positions": [
    {
      "code": "DL",
      "level": 20
    },
    {
      "code": "WBL",
      "level": 16
    },
    {
      "code": "AML",
      "level": 16
    }
  ],
  "current_ability": 59,
  "potential_ability": 94,
  "value": 57000,
  "contract": {
    "salary": 0,
    "expiration": "2028-05-31",
    "started": "2025-07-01",
    "contract_type": "FullTime"
  }
}