{
  "id": 2000149186,
  "first_name": "Ángel",
  "last_name": "Pérez",
  "birth_date": "2002-08-28",
  "country_id": 796,
  "club_id": 1688,
  "positions": [
    {
      "code": "DR",
      "level": 20
    },
    {
      "code": "WBR",
      "level": 16
    },
    {
      "code": "AMR",
      "level": 16
    }
  ],
  "current_ability": 88,
  "potential_ability": 109,
  "value": 864000,
  "contract": {
    "salary": 0,
    "expiration": "2030-06-30",
    "started": "2025-07-01",
    "contract_type": "FullTime"
  },
  "ids": {
    "transfermarkt.com": "1124136"
  }
}