{
  "id": 39035653,
  "first_name": "Arnór",
  "last_name": "Daði Aðalsteinsson",
  "birth_date": "1997-03-06",
  "country_id": 774,
  "club_id": 7840114,
  "positions": [
    {
      "code": "DL",
      "level": 20
    },
    {
      "code": "DC",
      "level": 20
    },
    {
      "code": "DM",
      "level": 20
    }
  ],
  "current_ability": 52,
  "potential_ability": 59,
  "value": 18000,
  "contract": {
    "salary": 0,
    "expiration": "2028-12-31",
    "started": "2025-07-01",
    "contract_type": "PartTime"
  }
}