{
  "id": 1301104,
  "name": "Rostov",
  "location": {
    "city_id": 107
  },
  "finance": {
    "balance": 21590000
  },
  "teams": [
    {
      "id": 1301104,
      "name": "Rostov",
      "slug": "rostov",
      "team_type": "Main",
      "reputation": {
        "home": 6000,
        "national": 6000,
        "world": 6000
      }
    },
    {
      "id": 99100015,
      "name": "Rostov",
      "slug": "rostov-u21",
      "team_type": "U21",
      "reputation": {
        "home": 1800,
        "national": 1800,
        "world": 1800
      }
    },
    {
      "id": 99100016,
      "name": "Rostov",
      "slug": "rostov-u19",
      "team_type": "U19",
      "reputation": {
        "home": 1200,
        "national": 1200,
        "world": 1200
      }
    }
  ],
  "colors": {
    "background": "#f7d716",
    "foreground": "#1a3c6e"
  },
  "philosophy": "Balanced",
  "facilities": {
    "training": "Average",
    "youth": "Adequate",
    "academy": "Average",
    "recruitment": "Adequate"
  },
  "average_attendance": 11725
}