{
  "id": 33020908,
  "first_name": "Jesse",
  "last_name": "Joronen",
  "birth_date": "1993-03-21",
  "country_id": 768,
  "club_id": 2194,
  "positions": [
    {
      "code": "GK",
      "level": 20
    }
  ],
  "current_ability": 91,
  "potential_ability": 107,
  "value": 814000,
  "contract": {
    "salary": 0,
    "expiration": "2028-06-30",
    "started": "2025-07-01",
    "contract_type": "FullTime"
  },
  "ids": {
    "transfermarkt.com": "131758"
  },
  "history": [
    { "s": 2024, "c": 1179, "p": 8 }
  ]
}