{
  "id": 96120693,
  "first_name": "Kacper",
  "last_name": "Gach",
  "birth_date": "1998-07-11",
  "country_id": 787,
  "club_id": 714200,
  "positions": [
    {
      "code": "DL",
      "level": 20
    },
    {
      "code": "WBL",
      "level": 16
    },
    {
      "code": "AML",
      "level": 16
    }
  ],
  "current_ability": 76,
  "potential_ability": 85,
  "value": 40000,
  "contract": {
    "salary": 0,
    "expiration": "2026-06-30",
    "started": "2025-07-01",
    "contract_type": "FullTime"
  }
}