{
  "id": 2000228292,
  "first_name": "Matej",
  "last_name": "Riznič",
  "birth_date": "2004-06-04",
  "country_id": 794,
  "club_id": 1301169,
  "positions": [
    {
      "code": "AML",
      "level": 20
    },
    {
      "code": "AMC",
      "level": 20
    }
  ],
  "current_ability": 81,
  "potential_ability": 106,
  "value": 163000,
  "contract": {
    "salary": 0,
    "expiration": "2028-06-30",
    "started": "2025-07-01",
    "contract_type": "FullTime"
  },
  "loan": {
    "to_club_id": 1300309,
    "expiration": "2027-06-20",
    "salary": 0,
    "wage_contribution_pct": 100
  },
  "ids": {
    "transfermarkt.com": "907630"
  }
}